retry/__init__.py
pipeline_utils_retry-1.1.0.dist-info/METADATA
pipeline_utils_retry-1.1.0.dist-info/WHEEL
pipeline_utils_retry-1.1.0.dist-info/top_level.txt
pipeline_utils_retry-1.1.0.dist-info/RECORD
