Metadata-Version: 2.1
Name: pipeline-utils-retry
Version: 1.1.0
Summary: A simple retry mechanism for Python functions
Project-URL: Homepage, https://github.com/pipeline-utils/retry
Classifier: Development Status :: 3 - Alpha
Classifier: Intended Audience :: Developers
Classifier: Programming Language :: Python :: 3
Classifier: Programming Language :: Python :: 3.8
Classifier: Programming Language :: Python :: 3.9
Classifier: Programming Language :: Python :: 3.10
Classifier: Programming Language :: Python :: 3.11
Requires-Python: >=3.8
